ghtest/__init__.py
ghtest/analyze_tests.py
ghtest/cassette_sanitizer.py
ghtest/cli.py
ghtest/core.py
ghtest/coverage_analysis.py
ghtest/create_tests_workflow.py
ghtest/param_suggestor.py
ghtest/scanner.py
ghtest/test_utils.py
ghtest/tests_creator.py
ghtest/tests_writer.py
ghtest/data/param_seed.json
ghtest-0.1.6.dist-info/METADATA
ghtest-0.1.6.dist-info/WHEEL
ghtest-0.1.6.dist-info/entry_points.txt
ghtest-0.1.6.dist-info/licenses/LICENSE.txt
ghtest-0.1.6.dist-info/RECORD
