Metadata-Version: 2.4
Name: ghtest
Version: 0.1.6
Summary: Coverage-guided test generator for Python
License-File: LICENSE.txt
Requires-Python: >=3.13
Requires-Dist: dill>=0.4.0
Requires-Dist: natsort>=8.4.0
Requires-Dist: pytest-cov>=5.0.0
Requires-Dist: pytest>=8.0.0
Requires-Dist: vcrpy>=6.0.0
